mtb/LUT.py
mtb/__init__.py
mtb/color.py
mtb/darkstyle.py
mtb/darkstyle.qrc
mtb/database.py
mtb/fileinfo.py
mtb/pyinstaller_helpers.py
mtb/qtEventsFilters.py
mtb/qtStyles.css
mtb/qtStyles.py
mtb/qtUtils.py
mtb/utils.py
mtb/video.py
mtb/video_prop.py
mtb/Image/__init__.py
mtb/Image/dom.py
mtb/Image/dominantColor.py
mtb/Image/image.py
mtb/Image/kmean.py
mtb/assets/off.wav
mtb/assets/on.wav
mtb/assets/LUTS/28 Days Later - Alexa Log-C.cube
mtb/assets/LUTS/30 Days of Night - Alexa Log-C.cube
mtb/assets/LUTS/Amityville Horror - Alexa Log-C.cube
mtb/assets/LUTS/Black Swan - Alexa Log-C.cube
mtb/assets/LUTS/Constantine - Alexa Log-C.cube
mtb/assets/LUTS/Crimson Peak - Alexa Log-C.cube
mtb/assets/LUTS/Dawn of the Dead (2004) - Alexa Log-C.cube
mtb/assets/LUTS/Friday The 13th - Alexa Log-C.cube
mtb/assets/LUTS/Hostel - Alexa Log-C.cube
mtb/assets/LUTS/Identity - Alexa Log-C.cube
mtb/assets/LUTS/Insidious - Alexa Log-C.cube
mtb/assets/LUTS/It Follows - Alexa Log-C.cube
mtb/assets/LUTS/Jaws - Alexa Log-C.cube
mtb/assets/LUTS/Let The Right One In (Morse) - Alexa Log-C.cube
mtb/assets/LUTS/Nightmare on Elm Street (2010) - Alexa Log-C.cube
mtb/assets/LUTS/Nightmare on Elm Street (Original) - Alexa Log-C.cube
mtb/assets/LUTS/Pitch Black - Alexa Log-C.cube
mtb/assets/LUTS/Poltergeist - Alexa Log-C.cube
mtb/assets/LUTS/Psycho - Alexa Log-C.cube
mtb/assets/LUTS/Resident Evil - Alexa Log-C.cube
mtb/assets/LUTS/Saw - Alexa Log-C.cube
mtb/assets/LUTS/Se7en - Alexa Log-C.cube
mtb/assets/LUTS/Sinister - Alexa Log-C.cube
mtb/assets/LUTS/Sixth Sense - Alexa Log-C.cube
mtb/assets/LUTS/Sleepy Hollow - Alexa Log-C.cube
mtb/assets/LUTS/Suspiria #1 - Alexa Log-C.cube
mtb/assets/LUTS/Suspiria #2 - Alexa Log-C.cube
mtb/assets/LUTS/Texas Chainsaw Massacre - Alexa Log-C.cube
mtb/assets/LUTS/The Babadook - Alexa Log-C.cube
mtb/assets/LUTS/The Cabin in the Woods - Alexa Log-C.cube
mtb/assets/LUTS/The Evil Dead - Alexa Log-C.cube
pymtb-0.1.2.dist-info/DESCRIPTION.rst
pymtb-0.1.2.dist-info/METADATA
pymtb-0.1.2.dist-info/RECORD
pymtb-0.1.2.dist-info/WHEEL
pymtb-0.1.2.dist-info/metadata.json
pymtb-0.1.2.dist-info/top_level.txt
